diahex2txt/__init__.py
diahex2txt/__main__.py
diahex2txt/decoder.py
diahex2txt/main.py
diahex2txt-1.0.0.dist-info/METADATA
diahex2txt-1.0.0.dist-info/WHEEL
diahex2txt-1.0.0.dist-info/entry_points.txt
diahex2txt-1.0.0.dist-info/licenses/LICENSE
diahex2txt-1.0.0.dist-info/RECORD
