Metadata-Version: 2.4
Name: diahex2txt
Version: 1.0.0
Summary: Decode hex-encoded Diameter messages into human-readable text
Project-URL: Homepage, https://github.com/fxyzbtc/diahex2txt
Project-URL: Repository, https://github.com/fxyzbtc/diahex2txt
Project-URL: Issues, https://github.com/fxyzbtc/diahex2txt/issues
Author-email: fxyzbtc <fxyzbtc@users.noreply.github.com>
License: MIT
License-File: LICENSE
Keywords: 3gpp,decoder,diameter,lte,protocol,telecom
Classifier: Development Status :: 4 - Beta
Classifier: Intended Audience :: Telecommunications Industry
Classifier: License :: OSI Approved :: MIT License
Classifier: Programming Language :: Python :: 3
Classifier: Programming Language :: Python :: 3.12
Classifier: Topic :: System :: Networking
Requires-Python: >=3.12
Requires-Dist: python-diameter>=0.7.1
Requires-Dist: typer>=0.9.0
